metalearners/__init__.py
metalearners/_narwhals_utils.py
metalearners/_typing.py
metalearners/_utils.py
metalearners/cross_fit_estimator.py
metalearners/data_generation.py
metalearners/drlearner.py
metalearners/explainer.py
metalearners/grid_search.py
metalearners/metalearner.py
metalearners/outcome_functions.py
metalearners/rlearner.py
metalearners/slearner.py
metalearners/tlearner.py
metalearners/utils.py
metalearners/xlearner.py
metalearners-0.13.0.dist-info/METADATA
metalearners-0.13.0.dist-info/WHEEL
metalearners-0.13.0.dist-info/licenses/LICENSE
metalearners-0.13.0.dist-info/RECORD
