Metadata-Version: 2.4
Name: metalearners
Version: 0.13.0
Summary: MetaLearners for CATE estimation
Project-URL: repository, https://github.com/quantco/metalearners
Author-email: "QuantCo, Inc." <noreply@quantco.com>
License-File: LICENSE
Classifier: License :: OSI Approved :: BSD License
Classifier: Operating System :: OS Independent
Classifier: Programming Language :: Python :: 3
Classifier: Programming Language :: Python :: 3.10
Classifier: Programming Language :: Python :: 3.11
Classifier: Programming Language :: Python :: 3.12
Requires-Python: >=3.10
Requires-Dist: joblib>=1.2.0
Requires-Dist: numpy
Requires-Dist: pandas
Requires-Dist: scikit-learn>=1.4
Requires-Dist: shap
Requires-Dist: typing-extensions
